main.py
aadfsadgfpklvhjcxoiasdssa-0.1.0.dist-info/METADATA
aadfsadgfpklvhjcxoiasdssa-0.1.0.dist-info/WHEEL
aadfsadgfpklvhjcxoiasdssa-0.1.0.dist-info/top_level.txt
aadfsadgfpklvhjcxoiasdssa-0.1.0.dist-info/RECORD
